odoo/addons/pos_hide_banknote_button/README.rst
odoo/addons/pos_hide_banknote_button/__init__.py
odoo/addons/pos_hide_banknote_button/__manifest__.py
odoo/addons/pos_hide_banknote_button/i18n/it.po
odoo/addons/pos_hide_banknote_button/i18n/pos_hide_banknote_button.pot
odoo/addons/pos_hide_banknote_button/readme/CONTRIBUTORS.rst
odoo/addons/pos_hide_banknote_button/readme/DESCRIPTION.rst
odoo/addons/pos_hide_banknote_button/static/description/after.png
odoo/addons/pos_hide_banknote_button/static/description/before.png
odoo/addons/pos_hide_banknote_button/static/description/icon.png
odoo/addons/pos_hide_banknote_button/static/description/index.html
odoo/addons/pos_hide_banknote_button/static/src/scss/pos_hide_banknote_button.scss
odoo_addon_pos_hide_banknote_button-16.0.1.0.0.3.dist-info/METADATA
odoo_addon_pos_hide_banknote_button-16.0.1.0.0.3.dist-info/WHEEL
odoo_addon_pos_hide_banknote_button-16.0.1.0.0.3.dist-info/top_level.txt
odoo_addon_pos_hide_banknote_button-16.0.1.0.0.3.dist-info/RECORD
